MANIFEST.in
README.md
requirements.txt
setup.py
threebot_repeat/__init__.py
threebot_repeat/admin.py
threebot_repeat/apps.py
threebot_repeat/checks.py
threebot_repeat/models.py
threebot_repeat/tasks.py
threebot_repeat/urls.py
threebot_repeat/views.py
threebot_repeat.egg-info/PKG-INFO
threebot_repeat.egg-info/SOURCES.txt
threebot_repeat.egg-info/dependency_links.txt
threebot_repeat.egg-info/requires.txt
threebot_repeat.egg-info/top_level.txt
threebot_repeat/management/__init__.py
threebot_repeat/management/commands/__init__.py
threebot_repeat/management/commands/hello.py
threebot_repeat/static/css/threebot_repeat.css
threebot_repeat/static/img/.gitignore
threebot_repeat/static/js/threebot_repeat.js
threebot_repeat/templates/threebot_repeat/list.html
threebot_repeat/templatetags/__init__.py
threebot_repeat/templatetags/threebot_repeat_tags.py