Metadata-Version: 1.1
Name: threebot-repeat
Version: 0.1.2
Summary: Add repetitive Task management to you 3bot
Home-page: UNKNOWN
Author: arteria GmbH
Author-email: admin@arteria.ch
License: UNKNOWN
Platform: UNKNOWN
Classifier: Intended Audience :: Developers
Classifier: Programming Language :: Python
Classifier: Programming Language :: Python :: 2
Classifier: Programming Language :: Python :: 2.7
Classifier: Topic :: Software Development :: Libraries :: Python Modules
Classifier: Framework :: Django
Classifier: License :: OSI Approved :: BSD License
Classifier: Development Status :: 4 - Beta
